nornir_nautobot_extensions/__init__.py
nornir_nautobot_extensions/plugins/__init__.py
nornir_nautobot_extensions/plugins/tasks/__init__.py
nornir_nautobot_extensions/plugins/tasks/dispatcher/__init__.py
nornir_nautobot_extensions/plugins/tasks/dispatcher/fortinet.py
nornir_nautobot_extensions-0.1.0.dist-info/AUTHORS.rst
nornir_nautobot_extensions-0.1.0.dist-info/LICENSE
nornir_nautobot_extensions-0.1.0.dist-info/METADATA
nornir_nautobot_extensions-0.1.0.dist-info/WHEEL
nornir_nautobot_extensions-0.1.0.dist-info/top_level.txt
nornir_nautobot_extensions-0.1.0.dist-info/RECORD
